spensireli/advanced_cdk_constructs/__init__.py
spensireli/advanced_cdk_constructs/py.typed
spensireli/advanced_cdk_constructs/_jsii/__init__.py
spensireli/advanced_cdk_constructs/_jsii/advanced-cdk-constructs@0.0.14.jsii.tgz
spensireli_advanced_cdk_constructs-0.0.14.dist-info/LICENSE
spensireli_advanced_cdk_constructs-0.0.14.dist-info/METADATA
spensireli_advanced_cdk_constructs-0.0.14.dist-info/WHEEL
spensireli_advanced_cdk_constructs-0.0.14.dist-info/top_level.txt
spensireli_advanced_cdk_constructs-0.0.14.dist-info/RECORD
